pcraft/Application.py
pcraft/Functions.py
pcraft/Plugins.py
pcraft/PluginsContext.py
pcraft/PluginsData.py
pcraft/Sessionizer.py
pcraft/__init__.py
pcraft/__version__.py
pcraft/functions/__init__.py
pcraft/functions/fromcsv.py
pcraft/functions/getvar.py
pcraft/functions/hostname.py
pcraft/plugins/Controller.py
pcraft/plugins/DNSConnection.py
pcraft/plugins/FakeNames.py
pcraft/plugins/GenerateNewDomain.py
pcraft/plugins/HTTPConnection.py
pcraft/plugins/HTTPPostConnection.py
pcraft/plugins/HostnameFromIP.py
pcraft/plugins/MakeVariables.py
pcraft/plugins/PcapImport.py
pcraft/plugins/Ping.py
pcraft/plugins/PrintVariables.py
pcraft/plugins/SMTPReceive.py
pcraft/plugins/Suricata.py
pcraft/plugins/TcpRst.py
pcraft/plugins/__init__.py
pcraft/plugins/_utils.py
pcraft-0.1.4.data/scripts/pcrafter
pcraft-0.1.4.dist-info/LICENSE
pcraft-0.1.4.dist-info/METADATA
pcraft-0.1.4.dist-info/WHEEL
pcraft-0.1.4.dist-info/top_level.txt
pcraft-0.1.4.dist-info/RECORD
