Metadata-Version: 2.1
Name: pcraft
Version: 0.1.4
Summary: Pcraft
Home-page: https://www.github.com/devoinc/pcraft
Author: Sebastien Tricaud
Author-email: sebastien.tricaud@devo.com
Maintainer: Sebastien Tricaud
Maintainer-email: sebastien.tricaud@devo.com
License: MIT
Platform: UNKNOWN
Classifier: Programming Language :: Python :: 3
Classifier: License :: OSI Approved :: MIT License
Classifier: Operating System :: OS Independent
Requires-Dist: scapy
Requires-Dist: IPy
Requires-Dist: PyYAML
Requires-Dist: dnspython
Requires-Dist: Faker
Requires-Dist: communityid
Requires-Dist: parsuricata
